{
 "category": "feat",
 "exclude_from_search": false,
 "feat": [
  "Dire Form"
 ],
 "feat_markdown": "Dire Form",
 "id": "feat-2496",
 "level": 13,
 "markdown": "<title\r\n    level=\"1\"\r\n    right=\"Feat 13\"\r\n    pfs=\"Standard\"\r\n>\r\n[Dire Form](/Feats.aspx?ID=2496) <actions string=\"\" />\r\n</title>\n\n<traits>\r\n<trait label=\"Beastkin\" url=\"/Traits.aspx?ID=337\" />\r\n</traits>\r\n\r\n<column gap=\"tiny\">\n\n**Source** [Ancestry Guide](/Sources.aspx?ID=74) pg. 81 <sup>3.0</sup>\n\n</column>\r\n\r\n---\r\n\r\nYour hybrid shape is a hulking beast. While in your hybrid shape, you gain the effects of [_enlarge_](/Spells.aspx?ID=102).",
 "name": "Dire Form",
 "pfs": "Standard",
 "primary_source": "Ancestry Guide",
 "primary_source_raw": "Ancestry Guide pg. 81",
 "primary_source_category": "Lost Omens",
 "rarity": "common",
 "rarity_id": 1,
 "release_date": "2021-02-24",
 "resistance": {},
 "search_markdown": "<traits>\r\n<trait label=\"Beastkin\" url=\"/Traits.aspx?ID=337\" />\r\n</traits>\r\n\r\n<additional-info>\r\n**Source** [Ancestry Guide](/Sources.aspx?ID=74) pg. 81 <sup>3.0</sup>\n\n</additional-info>\r\n\r\n---\r\n\r\n<summary>\r\nYour hybrid shape is a hulking beast.\r\n</summary>",
 "skill_mod": {},
 "source": [
  "Ancestry Guide"
 ],
 "source_raw": [
  "Ancestry Guide pg. 81"
 ],
 "source_category": [
  "Lost Omens"
 ],
 "source_markdown": "[Ancestry Guide](/Sources.aspx?ID=74) pg. 81 <sup>3.0</sup>",
 "speed": {},
 "summary": "Your hybrid shape is a hulking beast.",
 "summary_markdown": "Your hybrid shape is a hulking beast.",
 "text": "<title level=\"1\" right=\"Feat 13\" pfs=\"Standard\" > Dire Form Source Ancestry Guide pg. 81 3.0 --- Your hybrid shape is a hulking beast. While in your hybrid shape, you gain the effects of enlarge .",
 "trait": [
  "Beastkin"
 ],
 "trait_group": [
  "Ancestry"
 ],
 "trait_markdown": "[Beastkin](/Traits.aspx?ID=337)",
 "trait_raw": [
  "Beastkin"
 ],
 "type": "Feat",
 "url": "/Feats.aspx?ID=2496",
 "weakness": {}
}