{
 "base_item_markdown": "",
 "bulk": 0,
 "category": "equipment",
 "exclude_from_search": false,
 "id": "equipment-2836-2672",
 "item_category": "Runes",
 "item_parent_id": "equipment-2836",
 "item_subcategory": "Weapon Property Runes",
 "legacy_id": [
  "equipment-1055"
 ],
 "legacy_name": [
  "Extending"
 ],
 "level": 13,
 "markdown": "<title\r\n    level=\"1\"\r\n    right=\"Item 9+\"\r\n    pfs=\"Standard\"\r\n>\r\n[Extending](/Equipment.aspx?ID=2836)\r\n</title>\n\n<traits>\r\n<trait label=\"Magical\" url=\"/Traits.aspx?ID=644\" />\r\n</traits>\n\n<column gap=\"tiny\">\r\n\r\n**Source** [GM Core](/Sources.aspx?ID=218) pg. 237 <sup>2.0</sup>\n\n<row gap=\"medium\">\n\n**Usage** etched onto a melee weapon\n\n</row>\n\n<row gap=\"medium\">\n\n \r\n\r\n \r\n\r\n \r\n</row>\n\n</column>\r\n\r\n---\n\nAn extending rune allows you to extend your weapon to impossible lengths. \n\n**Activate—Extend** <actions string=\"Two Actions\" /> ([manipulate](/Traits.aspx?ID=104))    **Effect** You extend your weapon, giving you an impossible reach. You Strike with the weapon, and you have reach 60 feet for the Strike.\n\n<column gap=\"tiny\">\n\n</column>\r\n\r\n<title\r\nlevel=\"2\"\r\nright=\"Item 9\"\r\npfs=\"Standard\"\r\n>\r\nExtending\r\n</title>\n\n<traits>\r\n\r\n</traits>\r\n\r\n<column gap=\"tiny\">\r\n\r\n**Source** [GM Core](/Sources.aspx?ID=218) pg. 237 <sup>2.0</sup>, [Secrets of Magic](/Sources.aspx?ID=96) pg. 184 <sup>2.0</sup>\n\n**Price** 700 gp\r\n\r\n<row gap=\"medium\">\n\n</row>\n\n</column>\r\n\r\n<title\r\nlevel=\"2\"\r\nright=\"Item 13\"\r\npfs=\"Standard\"\r\n>\r\nExtending (Greater)\r\n</title>\n\n<traits>\r\n\r\n</traits>\r\n\r\n<column gap=\"tiny\">\r\n\r\n**Source** [GM Core](/Sources.aspx?ID=218) pg. 237 <sup>2.0</sup>, [Secrets of Magic](/Sources.aspx?ID=96) pg. 184 <sup>2.0</sup>\n\n**Price** 3,000 gp\r\n\r\n<row gap=\"medium\">\n\n</row>\n\n</column>\r\n\r\n---\r\n\r\nThe activation grants you reach 120 feet for the Strike.",
 "name": "Extending (Greater)",
 "pfs": "Standard",
 "price": 300000,
 "price_raw": "3,000 gp",
 "primary_source": "GM Core",
 "primary_source_raw": "GM Core pg. 237",
 "primary_source_category": "Rulebooks",
 "rarity": "common",
 "rarity_id": 1,
 "release_date": "2023-11-15",
 "resistance": {},
 "search_markdown": "<traits>\r\n<trait label=\"Magical\" url=\"/Traits.aspx?ID=644\" />\r\n</traits>\r\n\r\n<additional-info>\r\n**Source** [GM Core](/Sources.aspx?ID=218) pg. 237 <sup>2.0</sup>\r\n\r\n**Price** 3,000 gp\r\n\r\n<row gap=\"medium\">\r\n \r\n\r\n**Usage** etched onto a melee weapon\r\n\r\n \r\n</row>\n\n<row gap=\"medium\">\n\n \r\n\r\n \r\n</row>\r\n</additional-info>\r\n\r\n---\r\n\r\n<summary>\r\nThe activation grants you reach 120 feet for the Strike.\r\n</summary>",
 "skill_mod": {},
 "source": [
  "GM Core"
 ],
 "source_raw": [
  "GM Core pg. 237"
 ],
 "source_category": [
  "Rulebooks"
 ],
 "source_markdown": "[GM Core](/Sources.aspx?ID=218) pg. 237 <sup>2.0</sup>",
 "speed": {},
 "spell_markdown": "",
 "summary": "The activation grants you reach 120 feet for the Strike.",
 "summary_markdown": "The activation grants you reach 120 feet for the Strike.",
 "text": "<title level=\"1\" right=\"Item 9+\" pfs=\"Standard\" > Extending Source GM Core pg. 237 2.0 Usage etched onto a melee weapon --- An extending rune allows you to extend your weapon to impossible lengths. Activate—Extend Two Actions (manipulate) Effect You extend your weapon, giving you an impossible reach. You Strike with the weapon, and you have reach 60 feet for the Strike. <title level=\"2\" right=\"Item 9\" pfs=\"Standard\" > Extending Source GM Core pg. 237 2.0 , Secrets of Magic pg. 184 2.0 Price 700 gp <title level=\"2\" right=\"Item 13\" pfs=\"Standard\" > Extending (Greater) Source GM Core pg. 237 2.0 , Secrets of Magic pg. 184 2.0 Price 3,000 gp --- The activation grants you reach 120 feet for the Strike.",
 "trait": [
  "Magical"
 ],
 "trait_group": [
  "Mechanics"
 ],
 "trait_markdown": "[Magical](/Traits.aspx?ID=644)",
 "trait_raw": [
  "Magical"
 ],
 "type": "Item",
 "url": "/Equipment.aspx?ID=2836",
 "usage": "etched onto a melee weapon",
 "usage_markdown": "etched onto a melee weapon",
 "weakness": {}
}